Adafruit_BME280/BME280.py
Adafruit_BME280/__init__.py
Adafruit_BME280-1.0.1.dist-info/DESCRIPTION.rst
Adafruit_BME280-1.0.1.dist-info/METADATA
Adafruit_BME280-1.0.1.dist-info/RECORD
Adafruit_BME280-1.0.1.dist-info/WHEEL
Adafruit_BME280-1.0.1.dist-info/dependency_links.txt
Adafruit_BME280-1.0.1.dist-info/metadata.json
Adafruit_BME280-1.0.1.dist-info/top_level.txt
